nlptextprep/__init__.py
nlptextprep/preprocessing.py
nlptextprep/utils.py
nlptextprep-0.0.3.dist-info/LICENSE.txt
nlptextprep-0.0.3.dist-info/METADATA
nlptextprep-0.0.3.dist-info/WHEEL
nlptextprep-0.0.3.dist-info/top_level.txt
nlptextprep-0.0.3.dist-info/RECORD
