Metadata-Version: 2.1
Name: nlptextprep
Version: 0.0.3
Summary: One step Python package for NLP friendly data preprocessing.
Home-page: https://github.com/pyscaffold/pyscaffold/
Author: Tashu
Author-email: tashu@relinns.com
License: MIT
Project-URL: Documentation, https://pyscaffold.org/
Platform: any
Classifier: Development Status :: 4 - Beta
Classifier: Programming Language :: Python
License-File: LICENSE.txt
Requires-Dist: importlib-metadata ; python_version < "3.8"
Provides-Extra: testing
Requires-Dist: setuptools ; extra == 'testing'
Requires-Dist: pytest ; extra == 'testing'
Requires-Dist: pytest-cov ; extra == 'testing'
